{"procesos": {"generalPre": {"presidencial": {"CCODI_UBIGEO": "010702", "TNOMB_LOCAL": "IEI. N\u00ba 213", "TDIRE_LOCAL": "JR EL TRIUNFO SN", "CCENT_COMPU": "C45003", "DEPARTAMENTO": "AMAZONAS", "PROVINCIA": "UTCUBAMBA", "DISTRITO": "CAJARURO", "CCOPIA_ACTA": "96O", "NNUME_HABILM": 258, "OBSERVACION": "CONTABILIZADAS NORMALES", "OBSERVACION_TXT": "ACTA ELECTORAL NORMAL", "N_CANDIDATOS": 0, "TOT_CIUDADANOS_VOTARON": 151}, "votos": [{"CCODI_AUTO": "00000014", "AUTORIDAD": "PARTIDO POLITICO NACIONAL PERU LIBRE", "NLISTA": "1", "congresal": "92", "CON_VALIDOS": "69.173", "CON_EMITIDOS": "60.927"}, {"CCODI_AUTO": "00000007", "AUTORIDAD": "FUERZA POPULAR", "NLISTA": "2", "congresal": "41", "CON_VALIDOS": "30.827", "CON_EMITIDOS": "27.152"}, {"CCODI_AUTO": null, "AUTORIDAD": "TOTAL VOTOS VALIDOS", "congresal": "133", "CON_VALIDOS": "100.000", "CON_EMITIDOS": "88.079"}, {"CCODI_AUTO": "80", "AUTORIDAD": "VOTOS EN BLANCO", "congresal": "8", "CON_EMITIDOS": "5.298", "CON_VALIDOS": null}, {"CCODI_AUTO": "80", "AUTORIDAD": "VOTOS NULOS", "congresal": "10", "CON_EMITIDOS": "6.623", "CON_VALIDOS": null}, {"CCODI_AUTO": "80", "AUTORIDAD": "VOTOS IMPUGNADOS", "congresal": "0", "CON_EMITIDOS": "0.000", "CON_VALIDOS": null}, {"CCODI_AUTO": null, "AUTORIDAD": "TOTAL VOTOS EMITIDOS", "congresal": "151", "CON_EMITIDOS": "100.000", "CON_VALIDOS": "88.079"}], "resoluciones": [], "imageActa": "https://presentacionsep2021-actas-resultados-prod.s3.amazonaws.com/AC/C45003/SEP/ACPREC4500300084696.PDF?X-Amz-Algorithm=AWS4-HMAC-SHA256&X-Amz-Credential=AKIAXQU6GNJSVXR2WUHM%2F20210611%2Fus-east-1%2Fs3%2Faws4_request&X-Amz-Date=20210611T211406Z&X-Amz-Expires=3600&X-Amz-SignedHeaders=host&X-Amz-Signature=a1c1226569cf27cf50af1e2a09380b2706118a2c8db676323cc034e4687f53e1"}, "asistioNoVoto": "0", "realImages": "1"}}