{"procesos": {"generalPre": {"presidencial": {"CCODI_UBIGEO": "030307", "TNOMB_LOCAL": "54138", "TDIRE_LOCAL": "JR CCALLASPUQUIO SN", "CCENT_COMPU": "C45013", "DEPARTAMENTO": "APURIMAC", "PROVINCIA": "ANDAHUAYLAS", "DISTRITO": "PACOBAMBA", "CCOPIA_ACTA": "92A", "NNUME_HABILM": 300, "OBSERVACION": "CONTABILIZADAS NORMALES", "OBSERVACION_TXT": "ACTA ELECTORAL NORMAL", "N_CANDIDATOS": 0, "TOT_CIUDADANOS_VOTARON": 257}, "votos": [{"CCODI_AUTO": "00000014", "AUTORIDAD": "PARTIDO POLITICO NACIONAL PERU LIBRE", "NLISTA": "1", "congresal": "209", "CON_VALIDOS": "82.283", "CON_EMITIDOS": "81.323"}, {"CCODI_AUTO": "00000007", "AUTORIDAD": "FUERZA POPULAR", "NLISTA": "2", "congresal": "45", "CON_VALIDOS": "17.717", "CON_EMITIDOS": "17.510"}, {"CCODI_AUTO": null, "AUTORIDAD": "TOTAL VOTOS VALIDOS", "congresal": "254", "CON_VALIDOS": "100.000", "CON_EMITIDOS": "98.833"}, {"CCODI_AUTO": "80", "AUTORIDAD": "VOTOS EN BLANCO", "congresal": "1", "CON_EMITIDOS": "0.389", "CON_VALIDOS": null}, {"CCODI_AUTO": "80", "AUTORIDAD": "VOTOS NULOS", "congresal": "2", "CON_EMITIDOS": "0.778", "CON_VALIDOS": null}, {"CCODI_AUTO": "80", "AUTORIDAD": "VOTOS IMPUGNADOS", "congresal": "0", "CON_EMITIDOS": "0.000", "CON_VALIDOS": null}, {"CCODI_AUTO": null, "AUTORIDAD": "TOTAL VOTOS EMITIDOS", "congresal": "257", "CON_EMITIDOS": "100.000", "CON_VALIDOS": "98.833"}], "resoluciones": [], "imageActa": "https://presentacionsep2021-actas-resultados-prod2.s3.amazonaws.com/AC/C45013/SEP/ACPREC4501300427292.PDF?X-Amz-Algorithm=AWS4-HMAC-SHA256&X-Amz-Credential=AKIAXQU6GNJSVXR2WUHM%2F20210611%2Fus-east-2%2Fs3%2Faws4_request&X-Amz-Date=20210611T214801Z&X-Amz-Expires=3600&X-Amz-SignedHeaders=host&X-Amz-Signature=9210387d3965bb590fc248660303d07d455b030d61091dd5f1f3efbe4a8bfae7"}, "asistioNoVoto": "0", "realImages": "1"}}