{"procesos": {"generalPre": {"presidencial": {"CCODI_UBIGEO": "040118", "TNOMB_LOCAL": "IE 40073 VICTOR MANUEL PEROCHENA LUQUE", "TDIRE_LOCAL": "CALLE VICTOR A PEROCHENA SN", "CCENT_COMPU": "C45015", "DEPARTAMENTO": "AREQUIPA", "PROVINCIA": "AREQUIPA", "DISTRITO": "SANTA RITA DE SIHUAS", "CCOPIA_ACTA": "91O", "NNUME_HABILM": 280, "OBSERVACION": "CONTABILIZADAS NORMALES", "OBSERVACION_TXT": "ACTA ELECTORAL NORMAL", "N_CANDIDATOS": 0, "TOT_CIUDADANOS_VOTARON": 222}, "votos": [{"CCODI_AUTO": "00000014", "AUTORIDAD": "PARTIDO POLITICO NACIONAL PERU LIBRE", "NLISTA": "1", "congresal": "163", "CON_VALIDOS": "83.163", "CON_EMITIDOS": "73.423"}, {"CCODI_AUTO": "00000007", "AUTORIDAD": "FUERZA POPULAR", "NLISTA": "2", "congresal": "33", "CON_VALIDOS": "16.837", "CON_EMITIDOS": "14.865"}, {"CCODI_AUTO": null, "AUTORIDAD": "TOTAL VOTOS VALIDOS", "congresal": "196", "CON_VALIDOS": "100.000", "CON_EMITIDOS": "88.288"}, {"CCODI_AUTO": "80", "AUTORIDAD": "VOTOS EN BLANCO", "congresal": "2", "CON_EMITIDOS": "0.901", "CON_VALIDOS": null}, {"CCODI_AUTO": "80", "AUTORIDAD": "VOTOS NULOS", "congresal": "24", "CON_EMITIDOS": "10.811", "CON_VALIDOS": null}, {"CCODI_AUTO": "80", "AUTORIDAD": "VOTOS IMPUGNADOS", "congresal": "0", "CON_EMITIDOS": "0.000", "CON_VALIDOS": null}, {"CCODI_AUTO": null, "AUTORIDAD": "TOTAL VOTOS EMITIDOS", "congresal": "222", "CON_EMITIDOS": "100.000", "CON_VALIDOS": "88.288"}], "resoluciones": [], "imageActa": "https://presentacionsep2021-actas-resultados-prod2.s3.amazonaws.com/AC/C45015/SEP/ACPREC4501500659491.PDF?X-Amz-Algorithm=AWS4-HMAC-SHA256&X-Amz-Credential=AKIAXQU6GNJSVXR2WUHM%2F20210611%2Fus-east-2%2Fs3%2Faws4_request&X-Amz-Date=20210611T230657Z&X-Amz-Expires=3600&X-Amz-SignedHeaders=host&X-Amz-Signature=6723e975e265585edb39d806038c105c7421a7010ae329bda9094d9c34714dc8"}, "asistioNoVoto": "0", "realImages": "1"}}