{"procesos": {"generalPre": {"presidencial": {"CCODI_UBIGEO": "040301", "TNOMB_LOCAL": "IE 41041 CRISTO REY", "TDIRE_LOCAL": "JR SAN MARTIN SN", "CCENT_COMPU": "C45015", "DEPARTAMENTO": "AREQUIPA", "PROVINCIA": "CAMANA", "DISTRITO": "CAMANA", "CCOPIA_ACTA": "96O", "NNUME_HABILM": 300, "OBSERVACION": "CONTABILIZADAS NORMALES", "OBSERVACION_TXT": "ACTA ELECTORAL NORMAL", "N_CANDIDATOS": 0, "TOT_CIUDADANOS_VOTARON": 227}, "votos": [{"CCODI_AUTO": "00000014", "AUTORIDAD": "PARTIDO POLITICO NACIONAL PERU LIBRE", "NLISTA": "1", "congresal": "107", "CON_VALIDOS": "48.636", "CON_EMITIDOS": "47.137"}, {"CCODI_AUTO": "00000007", "AUTORIDAD": "FUERZA POPULAR", "NLISTA": "2", "congresal": "113", "CON_VALIDOS": "51.364", "CON_EMITIDOS": "49.780"}, {"CCODI_AUTO": null, "AUTORIDAD": "TOTAL VOTOS VALIDOS", "congresal": "220", "CON_VALIDOS": "100.000", "CON_EMITIDOS": "96.916"}, {"CCODI_AUTO": "80", "AUTORIDAD": "VOTOS EN BLANCO", "congresal": "0", "CON_EMITIDOS": "0.000", "CON_VALIDOS": null}, {"CCODI_AUTO": "80", "AUTORIDAD": "VOTOS NULOS", "congresal": "7", "CON_EMITIDOS": "3.084", "CON_VALIDOS": null}, {"CCODI_AUTO": "80", "AUTORIDAD": "VOTOS IMPUGNADOS", "congresal": "0", "CON_EMITIDOS": "0.000", "CON_VALIDOS": null}, {"CCODI_AUTO": null, "AUTORIDAD": "TOTAL VOTOS EMITIDOS", "congresal": "227", "CON_EMITIDOS": "100.000", "CON_VALIDOS": "96.916"}], "resoluciones": [], "imageActa": "https://presentacionsep2021-actas-resultados-prod2.s3.amazonaws.com/AC/C45015/SEP/ACPREC4501500817396.PDF?X-Amz-Algorithm=AWS4-HMAC-SHA256&X-Amz-Credential=AKIAXQU6GNJSVXR2WUHM%2F20210611%2Fus-east-2%2Fs3%2Faws4_request&X-Amz-Date=20210611T214405Z&X-Amz-Expires=3600&X-Amz-SignedHeaders=host&X-Amz-Signature=e9558a6c9691ffdae58c9744f965a0720072195d79a161f64181ffbafb65cf64"}, "asistioNoVoto": "0", "realImages": "1"}}