{"procesos": {"generalPre": {"presidencial": {"CCODI_UBIGEO": "070801", "TNOMB_LOCAL": "IE CORONEL LADISLAO ESPINAR", "TDIRE_LOCAL": "AV SAN MARTIN SN", "CCENT_COMPU": "C45035", "DEPARTAMENTO": "CUSCO", "PROVINCIA": "ESPINAR", "DISTRITO": "ESPINAR", "CCOPIA_ACTA": "96B", "NNUME_HABILM": 300, "OBSERVACION": "CONTABILIZADAS NORMALES", "OBSERVACION_TXT": "ACTA ELECTORAL NORMAL", "N_CANDIDATOS": 0, "TOT_CIUDADANOS_VOTARON": 232}, "votos": [{"CCODI_AUTO": "00000014", "AUTORIDAD": "PARTIDO POLITICO NACIONAL PERU LIBRE", "NLISTA": "1", "congresal": "197", "CON_VALIDOS": "91.628", "CON_EMITIDOS": "84.914"}, {"CCODI_AUTO": "00000007", "AUTORIDAD": "FUERZA POPULAR", "NLISTA": "2", "congresal": "18", "CON_VALIDOS": "8.372", "CON_EMITIDOS": "7.759"}, {"CCODI_AUTO": null, "AUTORIDAD": "TOTAL VOTOS VALIDOS", "congresal": "215", "CON_VALIDOS": "100.000", "CON_EMITIDOS": "92.672"}, {"CCODI_AUTO": "80", "AUTORIDAD": "VOTOS EN BLANCO", "congresal": "0", "CON_EMITIDOS": "0.000", "CON_VALIDOS": null}, {"CCODI_AUTO": "80", "AUTORIDAD": "VOTOS NULOS", "congresal": "17", "CON_EMITIDOS": "7.328", "CON_VALIDOS": null}, {"CCODI_AUTO": "80", "AUTORIDAD": "VOTOS IMPUGNADOS", "congresal": "0", "CON_EMITIDOS": "0.000", "CON_VALIDOS": null}, {"CCODI_AUTO": null, "AUTORIDAD": "TOTAL VOTOS EMITIDOS", "congresal": "232", "CON_EMITIDOS": "100.000", "CON_VALIDOS": "92.672"}], "resoluciones": [], "imageActa": "https://presentacionsep2021-actas-resultados-prod2.s3.amazonaws.com/AC/C45035/SEP/ACPREC4503501589496.PDF?X-Amz-Algorithm=AWS4-HMAC-SHA256&X-Amz-Credential=AKIAXQU6GNJSVXR2WUHM%2F20210611%2Fus-east-2%2Fs3%2Faws4_request&X-Amz-Date=20210611T215538Z&X-Amz-Expires=3600&X-Amz-SignedHeaders=host&X-Amz-Signature=89415cf32333ee12b5fb84f57366b6f4791981561376501fd3794fc7f68ce339"}, "asistioNoVoto": "0", "realImages": "1"}}