{"procesos": {"generalPre": {"presidencial": {"CCODI_UBIGEO": "090101", "TNOMB_LOCAL": "IE ECLESIAL LA IMACULADA CONCEPCION", "TDIRE_LOCAL": "JR HUANUCO CUADRA 2 SN", "CCENT_COMPU": "C45040", "DEPARTAMENTO": "HUANUCO", "PROVINCIA": "HUANUCO", "DISTRITO": "HUANUCO", "CCOPIA_ACTA": "97L", "NNUME_HABILM": 300, "OBSERVACION": "CONTABILIZADAS NORMALES", "OBSERVACION_TXT": "ACTA ELECTORAL NORMAL", "N_CANDIDATOS": 0, "TOT_CIUDADANOS_VOTARON": 224}, "votos": [{"CCODI_AUTO": "00000014", "AUTORIDAD": "PARTIDO POLITICO NACIONAL PERU LIBRE", "NLISTA": "1", "congresal": "119", "CON_VALIDOS": "57.767", "CON_EMITIDOS": "53.125"}, {"CCODI_AUTO": "00000007", "AUTORIDAD": "FUERZA POPULAR", "NLISTA": "2", "congresal": "87", "CON_VALIDOS": "42.233", "CON_EMITIDOS": "38.839"}, {"CCODI_AUTO": null, "AUTORIDAD": "TOTAL VOTOS VALIDOS", "congresal": "206", "CON_VALIDOS": "100.000", "CON_EMITIDOS": "91.964"}, {"CCODI_AUTO": "80", "AUTORIDAD": "VOTOS EN BLANCO", "congresal": "1", "CON_EMITIDOS": "0.446", "CON_VALIDOS": null}, {"CCODI_AUTO": "80", "AUTORIDAD": "VOTOS NULOS", "congresal": "17", "CON_EMITIDOS": "7.589", "CON_VALIDOS": null}, {"CCODI_AUTO": "80", "AUTORIDAD": "VOTOS IMPUGNADOS", "congresal": "0", "CON_EMITIDOS": "0.000", "CON_VALIDOS": null}, {"CCODI_AUTO": null, "AUTORIDAD": "TOTAL VOTOS EMITIDOS", "congresal": "224", "CON_EMITIDOS": "100.000", "CON_VALIDOS": "91.964"}], "resoluciones": [], "imageActa": "https://presentacionsep2021-actas-resultados-prod2.s3.amazonaws.com/AC/C45040/SEP/ACPREC4504001802397.PDF?X-Amz-Algorithm=AWS4-HMAC-SHA256&X-Amz-Credential=AKIAXQU6GNJSVXR2WUHM%2F20210611%2Fus-east-2%2Fs3%2Faws4_request&X-Amz-Date=20210611T214701Z&X-Amz-Expires=3600&X-Amz-SignedHeaders=host&X-Amz-Signature=8576edb1f17c756785177f0eb1a72f10efa9372037bba87af545d87ff1162233"}, "asistioNoVoto": "0", "realImages": "1"}}