{"procesos": {"generalPre": {"presidencial": {"CCODI_UBIGEO": "110108", "TNOMB_LOCAL": "IE JOSE MARIA ARGUEDAS", "TDIRE_LOCAL": "AV TUPAC AMARU 1012", "CCENT_COMPU": "C45046", "DEPARTAMENTO": "JUNIN", "PROVINCIA": "HUANCAYO", "DISTRITO": "CHILCA", "CCOPIA_ACTA": "91B", "NNUME_HABILM": 300, "OBSERVACION": "CONTABILIZADAS NORMALES", "OBSERVACION_TXT": "ACTA ELECTORAL NORMAL", "N_CANDIDATOS": 0, "TOT_CIUDADANOS_VOTARON": 237}, "votos": [{"CCODI_AUTO": "00000014", "AUTORIDAD": "PARTIDO POLITICO NACIONAL PERU LIBRE", "NLISTA": "1", "congresal": "157", "CON_VALIDOS": "70.089", "CON_EMITIDOS": "66.245"}, {"CCODI_AUTO": "00000007", "AUTORIDAD": "FUERZA POPULAR", "NLISTA": "2", "congresal": "67", "CON_VALIDOS": "29.911", "CON_EMITIDOS": "28.270"}, {"CCODI_AUTO": null, "AUTORIDAD": "TOTAL VOTOS VALIDOS", "congresal": "224", "CON_VALIDOS": "100.000", "CON_EMITIDOS": "94.515"}, {"CCODI_AUTO": "80", "AUTORIDAD": "VOTOS EN BLANCO", "congresal": "0", "CON_EMITIDOS": "0.000", "CON_VALIDOS": null}, {"CCODI_AUTO": "80", "AUTORIDAD": "VOTOS NULOS", "congresal": "13", "CON_EMITIDOS": "5.485", "CON_VALIDOS": null}, {"CCODI_AUTO": "80", "AUTORIDAD": "VOTOS IMPUGNADOS", "congresal": "0", "CON_EMITIDOS": "0.000", "CON_VALIDOS": null}, {"CCODI_AUTO": null, "AUTORIDAD": "TOTAL VOTOS EMITIDOS", "congresal": "237", "CON_EMITIDOS": "100.000", "CON_VALIDOS": "94.515"}], "resoluciones": [], "imageActa": "https://presentacionsep2021-actas-resultados-prod2.s3.amazonaws.com/AC/C45046/SEP/ACPREC4504602262991.PDF?X-Amz-Algorithm=AWS4-HMAC-SHA256&X-Amz-Credential=AKIAXQU6GNJSVXR2WUHM%2F20210611%2Fus-east-2%2Fs3%2Faws4_request&X-Amz-Date=20210611T215612Z&X-Amz-Expires=3600&X-Amz-SignedHeaders=host&X-Amz-Signature=9b3ec11dfd56ede68723aa4de073232616de0e368b7250a2b5cfc642c368ee9e"}, "asistioNoVoto": "0", "realImages": "1"}}