{"procesos": {"generalPre": {"presidencial": {"CCODI_UBIGEO": "110709", "TNOMB_LOCAL": "IE 31914 SAN MIGUEL DEL ENE", "TDIRE_LOCAL": "CALLE PRINCIPAL LOS HEROES SN", "CCENT_COMPU": "C45049", "DEPARTAMENTO": "JUNIN", "PROVINCIA": "SATIPO", "DISTRITO": "VIZCATAN DEL ENE", "CCOPIA_ACTA": "97K", "NNUME_HABILM": 280, "OBSERVACION": "CONTABILIZADAS NORMALES", "OBSERVACION_TXT": "ACTA ELECTORAL NORMAL", "N_CANDIDATOS": 0, "TOT_CIUDADANOS_VOTARON": 165}, "votos": [{"CCODI_AUTO": "00000014", "AUTORIDAD": "PARTIDO POLITICO NACIONAL PERU LIBRE", "NLISTA": "1", "congresal": "155", "CON_VALIDOS": "95.679", "CON_EMITIDOS": "93.939"}, {"CCODI_AUTO": "00000007", "AUTORIDAD": "FUERZA POPULAR", "NLISTA": "2", "congresal": "7", "CON_VALIDOS": "4.321", "CON_EMITIDOS": "4.242"}, {"CCODI_AUTO": null, "AUTORIDAD": "TOTAL VOTOS VALIDOS", "congresal": "162", "CON_VALIDOS": "100.000", "CON_EMITIDOS": "98.182"}, {"CCODI_AUTO": "80", "AUTORIDAD": "VOTOS EN BLANCO", "congresal": "0", "CON_EMITIDOS": "0.000", "CON_VALIDOS": null}, {"CCODI_AUTO": "80", "AUTORIDAD": "VOTOS NULOS", "congresal": "3", "CON_EMITIDOS": "1.818", "CON_VALIDOS": null}, {"CCODI_AUTO": "80", "AUTORIDAD": "VOTOS IMPUGNADOS", "congresal": "0", "CON_EMITIDOS": "0.000", "CON_VALIDOS": null}, {"CCODI_AUTO": null, "AUTORIDAD": "TOTAL VOTOS EMITIDOS", "congresal": "165", "CON_EMITIDOS": "100.000", "CON_VALIDOS": "98.182"}], "resoluciones": [], "imageActa": "https://presentacionsep2021-actas-resultados-prod2.s3.amazonaws.com/AC/C45049/SEP/ACPREC4504902478897.PDF?X-Amz-Algorithm=AWS4-HMAC-SHA256&X-Amz-Credential=AKIAXQU6GNJSVXR2WUHM%2F20210611%2Fus-east-2%2Fs3%2Faws4_request&X-Amz-Date=20210611T220642Z&X-Amz-Expires=3600&X-Amz-SignedHeaders=host&X-Amz-Signature=8859f00fc7203f5ed157053235054f8e7d3693ae63187d20a90dae58fa5cd70a"}, "asistioNoVoto": "0", "realImages": "1"}}