{"procesos": {"generalPre": {"presidencial": {"CCODI_UBIGEO": "120101", "TNOMB_LOCAL": "AREAS DEPORTIVAS PUERTA 03 DE LA IE SAN JUAN", "TDIRE_LOCAL": "AV SALVADOR LARA 450 PUERTA 03", "CCENT_COMPU": "C45050", "DEPARTAMENTO": "LA LIBERTAD", "PROVINCIA": "TRUJILLO", "DISTRITO": "TRUJILLO", "CCOPIA_ACTA": "96S", "NNUME_HABILM": 300, "OBSERVACION": "CONTABILIZADAS NORMALES", "OBSERVACION_TXT": "ACTA ELECTORAL NORMAL", "N_CANDIDATOS": 0, "TOT_CIUDADANOS_VOTARON": 246}, "votos": [{"CCODI_AUTO": "00000014", "AUTORIDAD": "PARTIDO POLITICO NACIONAL PERU LIBRE", "NLISTA": "1", "congresal": "78", "CON_VALIDOS": "34.361", "CON_EMITIDOS": "31.707"}, {"CCODI_AUTO": "00000007", "AUTORIDAD": "FUERZA POPULAR", "NLISTA": "2", "congresal": "149", "CON_VALIDOS": "65.639", "CON_EMITIDOS": "60.569"}, {"CCODI_AUTO": null, "AUTORIDAD": "TOTAL VOTOS VALIDOS", "congresal": "227", "CON_VALIDOS": "100.000", "CON_EMITIDOS": "92.276"}, {"CCODI_AUTO": "80", "AUTORIDAD": "VOTOS EN BLANCO", "congresal": "0", "CON_EMITIDOS": "0.000", "CON_VALIDOS": null}, {"CCODI_AUTO": "80", "AUTORIDAD": "VOTOS NULOS", "congresal": "19", "CON_EMITIDOS": "7.724", "CON_VALIDOS": null}, {"CCODI_AUTO": "80", "AUTORIDAD": "VOTOS IMPUGNADOS", "congresal": "0", "CON_EMITIDOS": "0.000", "CON_VALIDOS": null}, {"CCODI_AUTO": null, "AUTORIDAD": "TOTAL VOTOS EMITIDOS", "congresal": "246", "CON_EMITIDOS": "100.000", "CON_VALIDOS": "92.276"}], "resoluciones": [], "imageActa": "https://presentacionsep2021-actas-resultados-prod.s3.amazonaws.com/AC/C45050/SEP/ACPREC4505002609696.PDF?X-Amz-Algorithm=AWS4-HMAC-SHA256&X-Amz-Credential=AKIAXQU6GNJSVXR2WUHM%2F20210611%2Fus-east-1%2Fs3%2Faws4_request&X-Amz-Date=20210611T221919Z&X-Amz-Expires=3600&X-Amz-SignedHeaders=host&X-Amz-Signature=56da6ac57c26cd0560a019ed6a09ce7572d88d5f4d9b0327db3260d470bf6529"}, "asistioNoVoto": "0", "realImages": "1"}}