{"procesos": {"generalPre": {"presidencial": {"CCODI_UBIGEO": "120506", "TNOMB_LOCAL": "IE 80407 GONZALO UGAS SALCEDO", "TDIRE_LOCAL": "JR SARMIENTO 1012", "CCENT_COMPU": "C45053", "DEPARTAMENTO": "LA LIBERTAD", "PROVINCIA": "PACASMAYO", "DISTRITO": "PACASMAYO", "CCOPIA_ACTA": "94P", "NNUME_HABILM": 300, "OBSERVACION": "CONTABILIZADAS NORMALES", "OBSERVACION_TXT": "ACTA ELECTORAL NORMAL", "N_CANDIDATOS": 0, "TOT_CIUDADANOS_VOTARON": 166}, "votos": [{"CCODI_AUTO": "00000014", "AUTORIDAD": "PARTIDO POLITICO NACIONAL PERU LIBRE", "NLISTA": "1", "congresal": "67", "CON_VALIDOS": "44.667", "CON_EMITIDOS": "40.361"}, {"CCODI_AUTO": "00000007", "AUTORIDAD": "FUERZA POPULAR", "NLISTA": "2", "congresal": "83", "CON_VALIDOS": "55.333", "CON_EMITIDOS": "50.000"}, {"CCODI_AUTO": null, "AUTORIDAD": "TOTAL VOTOS VALIDOS", "congresal": "150", "CON_VALIDOS": "100.000", "CON_EMITIDOS": "90.361"}, {"CCODI_AUTO": "80", "AUTORIDAD": "VOTOS EN BLANCO", "congresal": "1", "CON_EMITIDOS": "0.602", "CON_VALIDOS": null}, {"CCODI_AUTO": "80", "AUTORIDAD": "VOTOS NULOS", "congresal": "15", "CON_EMITIDOS": "9.036", "CON_VALIDOS": null}, {"CCODI_AUTO": "80", "AUTORIDAD": "VOTOS IMPUGNADOS", "congresal": "0", "CON_EMITIDOS": "0.000", "CON_VALIDOS": null}, {"CCODI_AUTO": null, "AUTORIDAD": "TOTAL VOTOS EMITIDOS", "congresal": "166", "CON_EMITIDOS": "100.000", "CON_VALIDOS": "90.361"}], "resoluciones": [], "imageActa": "https://presentacionsep2021-actas-resultados-prod2.s3.amazonaws.com/AC/C45053/SEP/ACPREC4505302875994.PDF?X-Amz-Algorithm=AWS4-HMAC-SHA256&X-Amz-Credential=AKIAXQU6GNJSVXR2WUHM%2F20210611%2Fus-east-2%2Fs3%2Faws4_request&X-Amz-Date=20210611T225506Z&X-Amz-Expires=3600&X-Amz-SignedHeaders=host&X-Amz-Signature=266c9f0cbaad1a68d5b27edb87fbf93712e1b9264f31cb63fa9d9089bf93f5b1"}, "asistioNoVoto": "0", "realImages": "1"}}