{"procesos": {"generalPre": {"presidencial": {"CCODI_UBIGEO": "130112", "TNOMB_LOCAL": "IE EMBLEMATICA NICOLAS LA TORRE", "TDIRE_LOCAL": "AV SAENZ PE\u00d1A 1815", "CCENT_COMPU": "C45057", "DEPARTAMENTO": "LAMBAYEQUE", "PROVINCIA": "CHICLAYO", "DISTRITO": "JOSE LEONARDO ORTIZ", "CCOPIA_ACTA": "97G", "NNUME_HABILM": 300, "OBSERVACION": "CONTABILIZADAS NORMALES", "OBSERVACION_TXT": "ACTA ELECTORAL NORMAL", "N_CANDIDATOS": 0, "TOT_CIUDADANOS_VOTARON": 178}, "votos": [{"CCODI_AUTO": "00000014", "AUTORIDAD": "PARTIDO POLITICO NACIONAL PERU LIBRE", "NLISTA": "1", "congresal": "68", "CON_VALIDOS": "40.476", "CON_EMITIDOS": "38.202"}, {"CCODI_AUTO": "00000007", "AUTORIDAD": "FUERZA POPULAR", "NLISTA": "2", "congresal": "100", "CON_VALIDOS": "59.524", "CON_EMITIDOS": "56.180"}, {"CCODI_AUTO": null, "AUTORIDAD": "TOTAL VOTOS VALIDOS", "congresal": "168", "CON_VALIDOS": "100.000", "CON_EMITIDOS": "94.382"}, {"CCODI_AUTO": "80", "AUTORIDAD": "VOTOS EN BLANCO", "congresal": "2", "CON_EMITIDOS": "1.124", "CON_VALIDOS": null}, {"CCODI_AUTO": "80", "AUTORIDAD": "VOTOS NULOS", "congresal": "8", "CON_EMITIDOS": "4.494", "CON_VALIDOS": null}, {"CCODI_AUTO": "80", "AUTORIDAD": "VOTOS IMPUGNADOS", "congresal": "0", "CON_EMITIDOS": "0.000", "CON_VALIDOS": null}, {"CCODI_AUTO": null, "AUTORIDAD": "TOTAL VOTOS EMITIDOS", "congresal": "178", "CON_EMITIDOS": "100.000", "CON_VALIDOS": "94.382"}], "resoluciones": [], "imageActa": "https://presentacionsep2021-actas-resultados-prod2.s3.amazonaws.com/AC/C45057/SEP/ACPREC4505703176897.PDF?X-Amz-Algorithm=AWS4-HMAC-SHA256&X-Amz-Credential=AKIAXQU6GNJSVXR2WUHM%2F20210611%2Fus-east-2%2Fs3%2Faws4_request&X-Amz-Date=20210611T220952Z&X-Amz-Expires=3600&X-Amz-SignedHeaders=host&X-Amz-Signature=e258c5f4c968096286b360cc2e4ac8a738b01649c4b326134b06c88d061f7f06"}, "asistioNoVoto": "0", "realImages": "1"}}