{"procesos": {"generalPre": {"presidencial": {"CCODI_UBIGEO": "140103", "TNOMB_LOCAL": "IEP HERMANAS MISIONERAS DEL PERPETUO SOCORRO", "TDIRE_LOCAL": "EX FUNDO LA ESTRELLA MZ A LOTE 10", "CCENT_COMPU": "C45073", "DEPARTAMENTO": "LIMA", "PROVINCIA": "LIMA", "DISTRITO": "ATE", "CCOPIA_ACTA": "91L", "NNUME_HABILM": 300, "OBSERVACION": "CONTABILIZADAS NORMALES", "OBSERVACION_TXT": "ACTA ELECTORAL NORMAL", "N_CANDIDATOS": 0, "TOT_CIUDADANOS_VOTARON": 197}, "votos": [{"CCODI_AUTO": "00000014", "AUTORIDAD": "PARTIDO POLITICO NACIONAL PERU LIBRE", "NLISTA": "1", "congresal": "88", "CON_VALIDOS": "47.568", "CON_EMITIDOS": "44.670"}, {"CCODI_AUTO": "00000007", "AUTORIDAD": "FUERZA POPULAR", "NLISTA": "2", "congresal": "97", "CON_VALIDOS": "52.432", "CON_EMITIDOS": "49.239"}, {"CCODI_AUTO": null, "AUTORIDAD": "TOTAL VOTOS VALIDOS", "congresal": "185", "CON_VALIDOS": "100.000", "CON_EMITIDOS": "93.909"}, {"CCODI_AUTO": "80", "AUTORIDAD": "VOTOS EN BLANCO", "congresal": "1", "CON_EMITIDOS": "0.508", "CON_VALIDOS": null}, {"CCODI_AUTO": "80", "AUTORIDAD": "VOTOS NULOS", "congresal": "11", "CON_EMITIDOS": "5.584", "CON_VALIDOS": null}, {"CCODI_AUTO": "80", "AUTORIDAD": "VOTOS IMPUGNADOS", "congresal": "0", "CON_EMITIDOS": "0.000", "CON_VALIDOS": null}, {"CCODI_AUTO": null, "AUTORIDAD": "TOTAL VOTOS EMITIDOS", "congresal": "197", "CON_EMITIDOS": "100.000", "CON_VALIDOS": "93.909"}], "resoluciones": [], "imageActa": "https://presentacionsep2021-actas-resultados-prod2.s3.amazonaws.com/AC/C45073/SEP/ACPREC4507303559391.PDF?X-Amz-Algorithm=AWS4-HMAC-SHA256&X-Amz-Credential=AKIAXQU6GNJSVXR2WUHM%2F20210611%2Fus-east-2%2Fs3%2Faws4_request&X-Amz-Date=20210611T230920Z&X-Amz-Expires=3600&X-Amz-SignedHeaders=host&X-Amz-Signature=52a1704b2fc0fc6ab57c73df115b7a1e2684781cc46a0d678fb9498066b4b109"}, "asistioNoVoto": "0", "realImages": "1"}}