{"procesos": {"generalPre": {"presidencial": {"CCODI_UBIGEO": "140103", "TNOMB_LOCAL": "LOSA DEPORTIVA NI\u00d1O JESUS II ETAPA", "TDIRE_LOCAL": "FRENTE A MZ FLOTE 20 ASOCIACION NI\u00d1O JESUS", "CCENT_COMPU": "C45073", "DEPARTAMENTO": "LIMA", "PROVINCIA": "LIMA", "DISTRITO": "ATE", "CCOPIA_ACTA": "96S", "NNUME_HABILM": 300, "OBSERVACION": "CONTABILIZADAS NORMALES", "OBSERVACION_TXT": "ACTA ELECTORAL NORMAL", "N_CANDIDATOS": 0, "TOT_CIUDADANOS_VOTARON": 207}, "votos": [{"CCODI_AUTO": "00000014", "AUTORIDAD": "PARTIDO POLITICO NACIONAL PERU LIBRE", "NLISTA": "1", "congresal": "84", "CON_VALIDOS": "42.640", "CON_EMITIDOS": "40.580"}, {"CCODI_AUTO": "00000007", "AUTORIDAD": "FUERZA POPULAR", "NLISTA": "2", "congresal": "113", "CON_VALIDOS": "57.360", "CON_EMITIDOS": "54.589"}, {"CCODI_AUTO": null, "AUTORIDAD": "TOTAL VOTOS VALIDOS", "congresal": "197", "CON_VALIDOS": "100.000", "CON_EMITIDOS": "95.169"}, {"CCODI_AUTO": "80", "AUTORIDAD": "VOTOS EN BLANCO", "congresal": "3", "CON_EMITIDOS": "1.449", "CON_VALIDOS": null}, {"CCODI_AUTO": "80", "AUTORIDAD": "VOTOS NULOS", "congresal": "7", "CON_EMITIDOS": "3.382", "CON_VALIDOS": null}, {"CCODI_AUTO": "80", "AUTORIDAD": "VOTOS IMPUGNADOS", "congresal": "0", "CON_EMITIDOS": "0.000", "CON_VALIDOS": null}, {"CCODI_AUTO": null, "AUTORIDAD": "TOTAL VOTOS EMITIDOS", "congresal": "207", "CON_EMITIDOS": "100.000", "CON_VALIDOS": "95.169"}], "resoluciones": [], "imageActa": "https://presentacionsep2021-actas-resultados-prod2.s3.amazonaws.com/AC/C45073/SEP/ACPREC4507303576196.PDF?X-Amz-Algorithm=AWS4-HMAC-SHA256&X-Amz-Credential=AKIAXQU6GNJSVXR2WUHM%2F20210611%2Fus-east-2%2Fs3%2Faws4_request&X-Amz-Date=20210611T231039Z&X-Amz-Expires=3600&X-Amz-SignedHeaders=host&X-Amz-Signature=8675fbeb4b627dc0212b5f26faece8ce0d3fe8d143d90fb4bc0fb5384b4e1e4a"}, "asistioNoVoto": "0", "realImages": "1"}}