{"procesos": {"generalPre": {"presidencial": {"CCODI_UBIGEO": "140104", "TNOMB_LOCAL": "COLEGIO LA SALLE", "TDIRE_LOCAL": "AV ARICA 601", "CCENT_COMPU": "C45059", "DEPARTAMENTO": "LIMA", "PROVINCIA": "LIMA", "DISTRITO": "BRE\u00d1A", "CCOPIA_ACTA": "96L", "NNUME_HABILM": 300, "OBSERVACION": "CONTABILIZADAS NORMALES", "OBSERVACION_TXT": "ACTA ELECTORAL NORMAL", "N_CANDIDATOS": 0, "TOT_CIUDADANOS_VOTARON": 244}, "votos": [{"CCODI_AUTO": "00000014", "AUTORIDAD": "PARTIDO POLITICO NACIONAL PERU LIBRE", "NLISTA": "1", "congresal": "46", "CON_VALIDOS": "19.574", "CON_EMITIDOS": "18.852"}, {"CCODI_AUTO": "00000007", "AUTORIDAD": "FUERZA POPULAR", "NLISTA": "2", "congresal": "189", "CON_VALIDOS": "80.426", "CON_EMITIDOS": "77.459"}, {"CCODI_AUTO": null, "AUTORIDAD": "TOTAL VOTOS VALIDOS", "congresal": "235", "CON_VALIDOS": "100.000", "CON_EMITIDOS": "96.311"}, {"CCODI_AUTO": "80", "AUTORIDAD": "VOTOS EN BLANCO", "congresal": "0", "CON_EMITIDOS": "0.000", "CON_VALIDOS": null}, {"CCODI_AUTO": "80", "AUTORIDAD": "VOTOS NULOS", "congresal": "9", "CON_EMITIDOS": "3.689", "CON_VALIDOS": null}, {"CCODI_AUTO": "80", "AUTORIDAD": "VOTOS IMPUGNADOS", "congresal": "0", "CON_EMITIDOS": "0.000", "CON_VALIDOS": null}, {"CCODI_AUTO": null, "AUTORIDAD": "TOTAL VOTOS EMITIDOS", "congresal": "244", "CON_EMITIDOS": "100.000", "CON_VALIDOS": "96.311"}], "resoluciones": [], "imageActa": "https://presentacionsep2021-actas-resultados-prod2.s3.amazonaws.com/AC/C45059/SEP/ACPREC4505903598896.PDF?X-Amz-Algorithm=AWS4-HMAC-SHA256&X-Amz-Credential=AKIAXQU6GNJSVXR2WUHM%2F20210611%2Fus-east-2%2Fs3%2Faws4_request&X-Amz-Date=20210611T231221Z&X-Amz-Expires=3600&X-Amz-SignedHeaders=host&X-Amz-Signature=5ac13136c2edded60fd483bafed927a6affb5445f238c213021ccb103ba115a4"}, "asistioNoVoto": "0", "realImages": "1"}}