{"procesos": {"generalPre": {"presidencial": {"CCODI_UBIGEO": "140111", "TNOMB_LOCAL": "ESTADIO DE LA IE EMBLEMATICA MELIT\u00d3N CARBAJAL", "TDIRE_LOCAL": "AV LEONIDAS YEROVI 2120", "CCENT_COMPU": "C45065", "DEPARTAMENTO": "LIMA", "PROVINCIA": "LIMA", "DISTRITO": "LINCE", "CCOPIA_ACTA": "95K", "NNUME_HABILM": 300, "OBSERVACION": "CONTABILIZADAS NORMALES", "OBSERVACION_TXT": "ACTA ELECTORAL NORMAL", "N_CANDIDATOS": 0, "TOT_CIUDADANOS_VOTARON": 210}, "votos": [{"CCODI_AUTO": "00000014", "AUTORIDAD": "PARTIDO POLITICO NACIONAL PERU LIBRE", "NLISTA": "1", "congresal": "53", "CON_VALIDOS": "26.238", "CON_EMITIDOS": "25.238"}, {"CCODI_AUTO": "00000007", "AUTORIDAD": "FUERZA POPULAR", "NLISTA": "2", "congresal": "149", "CON_VALIDOS": "73.762", "CON_EMITIDOS": "70.952"}, {"CCODI_AUTO": null, "AUTORIDAD": "TOTAL VOTOS VALIDOS", "congresal": "202", "CON_VALIDOS": "100.000", "CON_EMITIDOS": "96.190"}, {"CCODI_AUTO": "80", "AUTORIDAD": "VOTOS EN BLANCO", "congresal": "0", "CON_EMITIDOS": "0.000", "CON_VALIDOS": null}, {"CCODI_AUTO": "80", "AUTORIDAD": "VOTOS NULOS", "congresal": "8", "CON_EMITIDOS": "3.810", "CON_VALIDOS": null}, {"CCODI_AUTO": "80", "AUTORIDAD": "VOTOS IMPUGNADOS", "congresal": "0", "CON_EMITIDOS": "0.000", "CON_VALIDOS": null}, {"CCODI_AUTO": null, "AUTORIDAD": "TOTAL VOTOS EMITIDOS", "congresal": "210", "CON_EMITIDOS": "100.000", "CON_VALIDOS": "96.190"}], "resoluciones": [], "imageActa": "https://presentacionsep2021-actas-resultados-prod.s3.amazonaws.com/AC/C45065/SEP/ACPREC4506504087595.PDF?X-Amz-Algorithm=AWS4-HMAC-SHA256&X-Amz-Credential=AKIAXQU6GNJSVXR2WUHM%2F20210611%2Fus-east-1%2Fs3%2Faws4_request&X-Amz-Date=20210611T223026Z&X-Amz-Expires=3600&X-Amz-SignedHeaders=host&X-Amz-Signature=9ab82f9838f26e5394fd6c3aac9722dc8e1530493dd5d9d5a830fc1e2fe4a508"}, "asistioNoVoto": "0", "realImages": "1"}}