{"procesos": {"generalPre": {"presidencial": {"CCODI_UBIGEO": "140119", "TNOMB_LOCAL": "DESPERTAR", "TDIRE_LOCAL": "MZ X LOTE 14 URB LAS FRESAS", "CCENT_COMPU": "C45064", "DEPARTAMENTO": "LIMA", "PROVINCIA": "LIMA", "DISTRITO": "PUENTE PIEDRA", "CCOPIA_ACTA": "94D", "NNUME_HABILM": 300, "OBSERVACION": "CONTABILIZADAS NORMALES", "OBSERVACION_TXT": "ACTA ELECTORAL NORMAL", "N_CANDIDATOS": 0, "TOT_CIUDADANOS_VOTARON": 229}, "votos": [{"CCODI_AUTO": "00000014", "AUTORIDAD": "PARTIDO POLITICO NACIONAL PERU LIBRE", "NLISTA": "1", "congresal": "78", "CON_VALIDOS": "45.882", "CON_EMITIDOS": "34.061"}, {"CCODI_AUTO": "00000007", "AUTORIDAD": "FUERZA POPULAR", "NLISTA": "2", "congresal": "92", "CON_VALIDOS": "54.118", "CON_EMITIDOS": "40.175"}, {"CCODI_AUTO": null, "AUTORIDAD": "TOTAL VOTOS VALIDOS", "congresal": "170", "CON_VALIDOS": "100.000", "CON_EMITIDOS": "74.236"}, {"CCODI_AUTO": "80", "AUTORIDAD": "VOTOS EN BLANCO", "congresal": "1", "CON_EMITIDOS": "0.437", "CON_VALIDOS": null}, {"CCODI_AUTO": "80", "AUTORIDAD": "VOTOS NULOS", "congresal": "58", "CON_EMITIDOS": "25.328", "CON_VALIDOS": null}, {"CCODI_AUTO": "80", "AUTORIDAD": "VOTOS IMPUGNADOS", "congresal": "0", "CON_EMITIDOS": "0.000", "CON_VALIDOS": null}, {"CCODI_AUTO": null, "AUTORIDAD": "TOTAL VOTOS EMITIDOS", "congresal": "229", "CON_EMITIDOS": "100.000", "CON_VALIDOS": "74.236"}], "resoluciones": [], "imageActa": "https://presentacionsep2021-actas-resultados-prod2.s3.amazonaws.com/AC/C45064/SEP/ACPREC4506404299594.PDF?X-Amz-Algorithm=AWS4-HMAC-SHA256&X-Amz-Credential=AKIAXQU6GNJSVXR2WUHM%2F20210611%2Fus-east-2%2Fs3%2Faws4_request&X-Amz-Date=20210611T231054Z&X-Amz-Expires=3600&X-Amz-SignedHeaders=host&X-Amz-Signature=49666b3220fd4ce68ec1645fca9920abc850d58ce14f9486d722f8ec2df687e8"}, "asistioNoVoto": "0", "realImages": "1"}}