{"procesos": {"generalPre": {"presidencial": {"CCODI_UBIGEO": "140119", "TNOMB_LOCAL": "IE 3092 KUMAMOTO I", "TDIRE_LOCAL": "AV 15 DE JUNIO SN", "CCENT_COMPU": "C45064", "DEPARTAMENTO": "LIMA", "PROVINCIA": "LIMA", "DISTRITO": "PUENTE PIEDRA", "CCOPIA_ACTA": "96U", "NNUME_HABILM": 300, "OBSERVACION": "CONTABILIZADAS NORMALES", "OBSERVACION_TXT": "ACTA ELECTORAL NORMAL", "N_CANDIDATOS": 0, "TOT_CIUDADANOS_VOTARON": 264}, "votos": [{"CCODI_AUTO": "00000014", "AUTORIDAD": "PARTIDO POLITICO NACIONAL PERU LIBRE", "NLISTA": "1", "congresal": "137", "CON_VALIDOS": "54.150", "CON_EMITIDOS": "51.894"}, {"CCODI_AUTO": "00000007", "AUTORIDAD": "FUERZA POPULAR", "NLISTA": "2", "congresal": "116", "CON_VALIDOS": "45.850", "CON_EMITIDOS": "43.939"}, {"CCODI_AUTO": null, "AUTORIDAD": "TOTAL VOTOS VALIDOS", "congresal": "253", "CON_VALIDOS": "100.000", "CON_EMITIDOS": "95.833"}, {"CCODI_AUTO": "80", "AUTORIDAD": "VOTOS EN BLANCO", "congresal": "4", "CON_EMITIDOS": "1.515", "CON_VALIDOS": null}, {"CCODI_AUTO": "80", "AUTORIDAD": "VOTOS NULOS", "congresal": "7", "CON_EMITIDOS": "2.652", "CON_VALIDOS": null}, {"CCODI_AUTO": "80", "AUTORIDAD": "VOTOS IMPUGNADOS", "congresal": "0", "CON_EMITIDOS": "0.000", "CON_VALIDOS": null}, {"CCODI_AUTO": null, "AUTORIDAD": "TOTAL VOTOS EMITIDOS", "congresal": "264", "CON_EMITIDOS": "100.000", "CON_VALIDOS": "95.833"}], "resoluciones": [], "imageActa": "https://presentacionsep2021-actas-resultados-prod2.s3.amazonaws.com/AC/C45064/SEP/ACPREC4506404334896.PDF?X-Amz-Algorithm=AWS4-HMAC-SHA256&X-Amz-Credential=AKIAXQU6GNJSVXR2WUHM%2F20210611%2Fus-east-2%2Fs3%2Faws4_request&X-Amz-Date=20210611T231620Z&X-Amz-Expires=3600&X-Amz-SignedHeaders=host&X-Amz-Signature=619132aeacaece9221bda3cfea7f8e3418ba459f78d5f388116b9e61cd2e1ec4"}, "asistioNoVoto": "0", "realImages": "1"}}