{"procesos": {"generalPre": {"presidencial": {"CCODI_UBIGEO": "140126", "TNOMB_LOCAL": "IE 2079 ANTONIO RAYMONDI", "TDIRE_LOCAL": "JR SAN BERNARDO SN - URB SANTA LUISA", "CCENT_COMPU": "C45061", "DEPARTAMENTO": "LIMA", "PROVINCIA": "LIMA", "DISTRITO": "SAN MARTIN DE PORRES", "CCOPIA_ACTA": "97L", "NNUME_HABILM": 300, "OBSERVACION": "CONTABILIZADAS NORMALES", "OBSERVACION_TXT": "ACTA ELECTORAL NORMAL", "N_CANDIDATOS": 0, "TOT_CIUDADANOS_VOTARON": 276}, "votos": [{"CCODI_AUTO": "00000014", "AUTORIDAD": "PARTIDO POLITICO NACIONAL PERU LIBRE", "NLISTA": "1", "congresal": "97", "CON_VALIDOS": "37.891", "CON_EMITIDOS": "35.145"}, {"CCODI_AUTO": "00000007", "AUTORIDAD": "FUERZA POPULAR", "NLISTA": "2", "congresal": "159", "CON_VALIDOS": "62.109", "CON_EMITIDOS": "57.609"}, {"CCODI_AUTO": null, "AUTORIDAD": "TOTAL VOTOS VALIDOS", "congresal": "256", "CON_VALIDOS": "100.000", "CON_EMITIDOS": "92.754"}, {"CCODI_AUTO": "80", "AUTORIDAD": "VOTOS EN BLANCO", "congresal": "2", "CON_EMITIDOS": "0.725", "CON_VALIDOS": null}, {"CCODI_AUTO": "80", "AUTORIDAD": "VOTOS NULOS", "congresal": "18", "CON_EMITIDOS": "6.522", "CON_VALIDOS": null}, {"CCODI_AUTO": "80", "AUTORIDAD": "VOTOS IMPUGNADOS", "congresal": "0", "CON_EMITIDOS": "0.000", "CON_VALIDOS": null}, {"CCODI_AUTO": null, "AUTORIDAD": "TOTAL VOTOS EMITIDOS", "congresal": "276", "CON_EMITIDOS": "100.000", "CON_VALIDOS": "92.754"}], "resoluciones": [], "imageActa": "https://presentacionsep2021-actas-resultados-prod2.s3.amazonaws.com/AC/C45061/SEP/ACPREC4506104479297.PDF?X-Amz-Algorithm=AWS4-HMAC-SHA256&X-Amz-Credential=AKIAXQU6GNJSVXR2WUHM%2F20210611%2Fus-east-2%2Fs3%2Faws4_request&X-Amz-Date=20210611T230313Z&X-Amz-Expires=3600&X-Amz-SignedHeaders=host&X-Amz-Signature=4bcf76f07285aa09d8f49717e435620a837b8389081eb7776e16c476ffd069bc"}, "asistioNoVoto": "0", "realImages": "1"}}