{"procesos": {"generalPre": {"presidencial": {"CCODI_UBIGEO": "140126", "TNOMB_LOCAL": "IEP SCHOOL TALENT", "TDIRE_LOCAL": "JR LOS HEROES 109", "CCENT_COMPU": "C45061", "DEPARTAMENTO": "LIMA", "PROVINCIA": "LIMA", "DISTRITO": "SAN MARTIN DE PORRES", "CCOPIA_ACTA": "93V", "NNUME_HABILM": 300, "OBSERVACION": "CONTABILIZADAS NORMALES", "OBSERVACION_TXT": "ACTA ELECTORAL NORMAL", "N_CANDIDATOS": 0, "TOT_CIUDADANOS_VOTARON": 224}, "votos": [{"CCODI_AUTO": "00000014", "AUTORIDAD": "PARTIDO POLITICO NACIONAL PERU LIBRE", "NLISTA": "1", "congresal": "53", "CON_VALIDOS": "25.238", "CON_EMITIDOS": "23.661"}, {"CCODI_AUTO": "00000007", "AUTORIDAD": "FUERZA POPULAR", "NLISTA": "2", "congresal": "157", "CON_VALIDOS": "74.762", "CON_EMITIDOS": "70.089"}, {"CCODI_AUTO": null, "AUTORIDAD": "TOTAL VOTOS VALIDOS", "congresal": "210", "CON_VALIDOS": "100.000", "CON_EMITIDOS": "93.750"}, {"CCODI_AUTO": "80", "AUTORIDAD": "VOTOS EN BLANCO", "congresal": "1", "CON_EMITIDOS": "0.446", "CON_VALIDOS": null}, {"CCODI_AUTO": "80", "AUTORIDAD": "VOTOS NULOS", "congresal": "13", "CON_EMITIDOS": "5.804", "CON_VALIDOS": null}, {"CCODI_AUTO": "80", "AUTORIDAD": "VOTOS IMPUGNADOS", "congresal": "0", "CON_EMITIDOS": "0.000", "CON_VALIDOS": null}, {"CCODI_AUTO": null, "AUTORIDAD": "TOTAL VOTOS EMITIDOS", "congresal": "224", "CON_EMITIDOS": "100.000", "CON_VALIDOS": "93.750"}], "resoluciones": [], "imageActa": "https://presentacionsep2021-actas-resultados-prod2.s3.amazonaws.com/AC/C45061/SEP/ACPREC4506104504293.PDF?X-Amz-Algorithm=AWS4-HMAC-SHA256&X-Amz-Credential=AKIAXQU6GNJSVXR2WUHM%2F20210611%2Fus-east-2%2Fs3%2Faws4_request&X-Amz-Date=20210611T230456Z&X-Amz-Expires=3600&X-Amz-SignedHeaders=host&X-Amz-Signature=575ff7076f07d1c5dbecd06845acf6dbe4e3a5b7fd94873342cbaa6501da7022"}, "asistioNoVoto": "0", "realImages": "1"}}