{"procesos": {"generalPre": {"presidencial": {"CCODI_UBIGEO": "140126", "TNOMB_LOCAL": "IE EMBLEMATICA JOSE GRANDA", "TDIRE_LOCAL": "AV UNIVERSITARIA 222", "CCENT_COMPU": "C45061", "DEPARTAMENTO": "LIMA", "PROVINCIA": "LIMA", "DISTRITO": "SAN MARTIN DE PORRES", "CCOPIA_ACTA": "95D", "NNUME_HABILM": 300, "OBSERVACION": "CONTABILIZADAS NORMALES", "OBSERVACION_TXT": "ACTA ELECTORAL NORMAL", "N_CANDIDATOS": 0, "TOT_CIUDADANOS_VOTARON": 158}, "votos": [{"CCODI_AUTO": "00000014", "AUTORIDAD": "PARTIDO POLITICO NACIONAL PERU LIBRE", "NLISTA": "1", "congresal": "47", "CON_VALIDOS": "31.544", "CON_EMITIDOS": "29.747"}, {"CCODI_AUTO": "00000007", "AUTORIDAD": "FUERZA POPULAR", "NLISTA": "2", "congresal": "102", "CON_VALIDOS": "68.456", "CON_EMITIDOS": "64.557"}, {"CCODI_AUTO": null, "AUTORIDAD": "TOTAL VOTOS VALIDOS", "congresal": "149", "CON_VALIDOS": "100.000", "CON_EMITIDOS": "94.304"}, {"CCODI_AUTO": "80", "AUTORIDAD": "VOTOS EN BLANCO", "congresal": "3", "CON_EMITIDOS": "1.899", "CON_VALIDOS": null}, {"CCODI_AUTO": "80", "AUTORIDAD": "VOTOS NULOS", "congresal": "6", "CON_EMITIDOS": "3.797", "CON_VALIDOS": null}, {"CCODI_AUTO": "80", "AUTORIDAD": "VOTOS IMPUGNADOS", "congresal": "0", "CON_EMITIDOS": "0.000", "CON_VALIDOS": null}, {"CCODI_AUTO": null, "AUTORIDAD": "TOTAL VOTOS EMITIDOS", "congresal": "158", "CON_EMITIDOS": "100.000", "CON_VALIDOS": "94.304"}], "resoluciones": [], "imageActa": "https://presentacionsep2021-actas-resultados-prod2.s3.amazonaws.com/AC/C45061/SEP/ACPREC4506104642695.PDF?X-Amz-Algorithm=AWS4-HMAC-SHA256&X-Amz-Credential=AKIAXQU6GNJSVXR2WUHM%2F20210611%2Fus-east-2%2Fs3%2Faws4_request&X-Amz-Date=20210611T231428Z&X-Amz-Expires=3600&X-Amz-SignedHeaders=host&X-Amz-Signature=ecc8badb8b759c7f6fa87f9b1b80847536f9a742496a25567522b84713ed3d4d"}, "asistioNoVoto": "0", "realImages": "1"}}