{"procesos": {"generalPre": {"presidencial": {"CCODI_UBIGEO": "140127", "TNOMB_LOCAL": "COMPLEJO DEPORTIVO PAUL HARRIES", "TDIRE_LOCAL": "CALLE LAS AMERICAS SN", "CCENT_COMPU": "C45065", "DEPARTAMENTO": "LIMA", "PROVINCIA": "LIMA", "DISTRITO": "SAN MIGUEL", "CCOPIA_ACTA": "95V", "NNUME_HABILM": 300, "OBSERVACION": "CONTABILIZADAS NORMALES", "OBSERVACION_TXT": "ACTA ELECTORAL RESUELTA", "N_CANDIDATOS": 0, "TOT_CIUDADANOS_VOTARON": 219}, "votos": [{"CCODI_AUTO": "00000014", "AUTORIDAD": "PARTIDO POLITICO NACIONAL PERU LIBRE", "NLISTA": "1", "congresal": "25", "CON_VALIDOS": "11.737", "CON_EMITIDOS": "11.416"}, {"CCODI_AUTO": "00000007", "AUTORIDAD": "FUERZA POPULAR", "NLISTA": "2", "congresal": "188", "CON_VALIDOS": "88.263", "CON_EMITIDOS": "85.845"}, {"CCODI_AUTO": null, "AUTORIDAD": "TOTAL VOTOS VALIDOS", "congresal": "213", "CON_VALIDOS": "100.000", "CON_EMITIDOS": "97.260"}, {"CCODI_AUTO": "80", "AUTORIDAD": "VOTOS EN BLANCO", "congresal": "0", "CON_EMITIDOS": "0.000", "CON_VALIDOS": null}, {"CCODI_AUTO": "80", "AUTORIDAD": "VOTOS NULOS", "congresal": "6", "CON_EMITIDOS": "2.740", "CON_VALIDOS": null}, {"CCODI_AUTO": "80", "AUTORIDAD": "VOTOS IMPUGNADOS", "congresal": "0", "CON_EMITIDOS": "0.000", "CON_VALIDOS": null}, {"CCODI_AUTO": null, "AUTORIDAD": "TOTAL VOTOS EMITIDOS", "congresal": "219", "CON_EMITIDOS": "100.000", "CON_VALIDOS": "97.260"}], "resoluciones": [{"CCENT_COMPU": "C45065", "CNUME_RESOL": "C45065000008", "CPROCED_RESOL": "JE", "CNUME_RESOL_JNE": "SEPEG 2021001413                                  06448-2021-JEE-LIO1/JNE", "CESTADO_RESOL": "P", "CNUME_ACTA": "046590", "IMAGEN": "https://presentacionsep2021-actas-resultados-prod2.s3.amazonaws.com/RE/C45065/SEP/RESEPC45065000008.PDF?X-Amz-Algorithm=AWS4-HMAC-SHA256&X-Amz-Credential=AKIAXQU6GNJSVXR2WUHM%2F20210611%2Fus-east-2%2Fs3%2Faws4_request&X-Amz-Date=20210611T231532Z&X-Amz-Expires=3600&X-Amz-SignedHeaders=host&X-Amz-Signature=7a5f3e7a9eed846d14e32c6fc872347a28e98ea8ba03054e81c76bf91e8692fd"}], "imageActa": "https://presentacionsep2021-actas-resultados-prod2.s3.amazonaws.com/AO/C45065/SEP/ACPREC4506504659095.PDF?X-Amz-Algorithm=AWS4-HMAC-SHA256&X-Amz-Credential=AKIAXQU6GNJSVXR2WUHM%2F20210611%2Fus-east-2%2Fs3%2Faws4_request&X-Amz-Date=20210611T231533Z&X-Amz-Expires=3600&X-Amz-SignedHeaders=host&X-Amz-Signature=128f276b8971f7d9bfcc0a601e33d86a4af4ac1d366734b5824d535a801bd01c"}, "asistioNoVoto": "0", "realImages": "1"}}