{"procesos": {"generalPre": {"presidencial": {"CCODI_UBIGEO": "140137", "TNOMB_LOCAL": "ULADECH", "TDIRE_LOCAL": "AV SANTA ROSA DE LIMA 1231", "CCENT_COMPU": "C45075", "DEPARTAMENTO": "LIMA", "PROVINCIA": "LIMA", "DISTRITO": "SAN JUAN DE LURIGANCHO", "CCOPIA_ACTA": "91K", "NNUME_HABILM": 300, "OBSERVACION": "CONTABILIZADAS NORMALES", "OBSERVACION_TXT": "ACTA ELECTORAL NORMAL", "N_CANDIDATOS": 0, "TOT_CIUDADANOS_VOTARON": 224}, "votos": [{"CCODI_AUTO": "00000014", "AUTORIDAD": "PARTIDO POLITICO NACIONAL PERU LIBRE", "NLISTA": "1", "congresal": "100", "CON_VALIDOS": "46.948", "CON_EMITIDOS": "44.643"}, {"CCODI_AUTO": "00000007", "AUTORIDAD": "FUERZA POPULAR", "NLISTA": "2", "congresal": "113", "CON_VALIDOS": "53.052", "CON_EMITIDOS": "50.446"}, {"CCODI_AUTO": null, "AUTORIDAD": "TOTAL VOTOS VALIDOS", "congresal": "213", "CON_VALIDOS": "100.000", "CON_EMITIDOS": "95.089"}, {"CCODI_AUTO": "80", "AUTORIDAD": "VOTOS EN BLANCO", "congresal": "2", "CON_EMITIDOS": "0.893", "CON_VALIDOS": null}, {"CCODI_AUTO": "80", "AUTORIDAD": "VOTOS NULOS", "congresal": "9", "CON_EMITIDOS": "4.018", "CON_VALIDOS": null}, {"CCODI_AUTO": "80", "AUTORIDAD": "VOTOS IMPUGNADOS", "congresal": "0", "CON_EMITIDOS": "0.000", "CON_VALIDOS": null}, {"CCODI_AUTO": null, "AUTORIDAD": "TOTAL VOTOS EMITIDOS", "congresal": "224", "CON_EMITIDOS": "100.000", "CON_VALIDOS": "95.089"}], "resoluciones": [], "imageActa": "https://presentacionsep2021-actas-resultados-prod.s3.amazonaws.com/AC/C45075/SEP/ACPREC4507505343591.PDF?X-Amz-Algorithm=AWS4-HMAC-SHA256&X-Amz-Credential=AKIAXQU6GNJSVXR2WUHM%2F20210611%2Fus-east-1%2Fs3%2Faws4_request&X-Amz-Date=20210611T234041Z&X-Amz-Expires=3600&X-Amz-SignedHeaders=host&X-Amz-Signature=f815f6ff9e47c1235e1b148c1bd8ab5ccf856c81b0d1577c3edc3ed64a3b8d67"}, "asistioNoVoto": "0", "realImages": "1"}}