{"procesos": {"generalPre": {"presidencial": {"CCODI_UBIGEO": "200101", "TNOMB_LOCAL": "IEP 70024 LAYKAKOTA", "TDIRE_LOCAL": "JR BANCHERO ROSSI 291", "CCENT_COMPU": "C45093", "DEPARTAMENTO": "PUNO", "PROVINCIA": "PUNO", "DISTRITO": "PUNO", "CCOPIA_ACTA": "97K", "NNUME_HABILM": 300, "OBSERVACION": "CONTABILIZADAS NORMALES", "OBSERVACION_TXT": "ACTA ELECTORAL NORMAL", "N_CANDIDATOS": 0, "TOT_CIUDADANOS_VOTARON": 210}, "votos": [{"CCODI_AUTO": "00000014", "AUTORIDAD": "PARTIDO POLITICO NACIONAL PERU LIBRE", "NLISTA": "1", "congresal": "168", "CON_VALIDOS": "82.353", "CON_EMITIDOS": "80.000"}, {"CCODI_AUTO": "00000007", "AUTORIDAD": "FUERZA POPULAR", "NLISTA": "2", "congresal": "36", "CON_VALIDOS": "17.647", "CON_EMITIDOS": "17.143"}, {"CCODI_AUTO": null, "AUTORIDAD": "TOTAL VOTOS VALIDOS", "congresal": "204", "CON_VALIDOS": "100.000", "CON_EMITIDOS": "97.143"}, {"CCODI_AUTO": "80", "AUTORIDAD": "VOTOS EN BLANCO", "congresal": "0", "CON_EMITIDOS": "0.000", "CON_VALIDOS": null}, {"CCODI_AUTO": "80", "AUTORIDAD": "VOTOS NULOS", "congresal": "6", "CON_EMITIDOS": "2.857", "CON_VALIDOS": null}, {"CCODI_AUTO": "80", "AUTORIDAD": "VOTOS IMPUGNADOS", "congresal": "0", "CON_EMITIDOS": "0.000", "CON_VALIDOS": null}, {"CCODI_AUTO": null, "AUTORIDAD": "TOTAL VOTOS EMITIDOS", "congresal": "210", "CON_EMITIDOS": "100.000", "CON_VALIDOS": "97.143"}], "resoluciones": [], "imageActa": "https://presentacionsep2021-actas-resultados-prod.s3.amazonaws.com/AC/C45093/SEP/ACPREC4509306958897.PDF?X-Amz-Algorithm=AWS4-HMAC-SHA256&X-Amz-Credential=AKIAXQU6GNJSVXR2WUHM%2F20210611%2Fus-east-1%2Fs3%2Faws4_request&X-Amz-Date=20210611T233822Z&X-Amz-Expires=3600&X-Amz-SignedHeaders=host&X-Amz-Signature=8b0c26145e91eadf17c81dc54860c29e0a61b82be8a5b04ed8c5243b71b2ac65"}, "asistioNoVoto": "0", "realImages": "1"}}