{"procesos": {"generalPre": {"presidencial": {"CCODI_UBIGEO": "210601", "TNOMB_LOCAL": "IE 0556", "TDIRE_LOCAL": "JR LAS ORQUIDES SN", "CCENT_COMPU": "C45098", "DEPARTAMENTO": "SAN MARTIN", "PROVINCIA": "SAN MARTIN", "DISTRITO": "TARAPOTO", "CCOPIA_ACTA": "92K", "NNUME_HABILM": 300, "OBSERVACION": "CONTABILIZADAS NORMALES", "OBSERVACION_TXT": "ACTA ELECTORAL NORMAL", "N_CANDIDATOS": 0, "TOT_CIUDADANOS_VOTARON": 218}, "votos": [{"CCODI_AUTO": "00000014", "AUTORIDAD": "PARTIDO POLITICO NACIONAL PERU LIBRE", "NLISTA": "1", "congresal": "73", "CON_VALIDOS": "36.500", "CON_EMITIDOS": "33.486"}, {"CCODI_AUTO": "00000007", "AUTORIDAD": "FUERZA POPULAR", "NLISTA": "2", "congresal": "127", "CON_VALIDOS": "63.500", "CON_EMITIDOS": "58.257"}, {"CCODI_AUTO": null, "AUTORIDAD": "TOTAL VOTOS VALIDOS", "congresal": "200", "CON_VALIDOS": "100.000", "CON_EMITIDOS": "91.743"}, {"CCODI_AUTO": "80", "AUTORIDAD": "VOTOS EN BLANCO", "congresal": "2", "CON_EMITIDOS": "0.917", "CON_VALIDOS": null}, {"CCODI_AUTO": "80", "AUTORIDAD": "VOTOS NULOS", "congresal": "16", "CON_EMITIDOS": "7.339", "CON_VALIDOS": null}, {"CCODI_AUTO": "80", "AUTORIDAD": "VOTOS IMPUGNADOS", "congresal": "0", "CON_EMITIDOS": "0.000", "CON_VALIDOS": null}, {"CCODI_AUTO": null, "AUTORIDAD": "TOTAL VOTOS EMITIDOS", "congresal": "218", "CON_EMITIDOS": "100.000", "CON_VALIDOS": "91.743"}], "resoluciones": [], "imageActa": "https://presentacionsep2021-actas-resultados-prod.s3.amazonaws.com/AC/C45098/SEP/ACPREC4509807343192.PDF?X-Amz-Algorithm=AWS4-HMAC-SHA256&X-Amz-Credential=AKIAXQU6GNJSVXR2WUHM%2F20210611%2Fus-east-1%2Fs3%2Faws4_request&X-Amz-Date=20210611T234622Z&X-Amz-Expires=3600&X-Amz-SignedHeaders=host&X-Amz-Signature=8d061ab2c06e556d39e0df584609c152d58a39b594b7ff7b68d11f0048de7bf1"}, "asistioNoVoto": "0", "realImages": "1"}}