{"procesos": {"generalPre": {"presidencial": {"CCODI_UBIGEO": "210620", "TNOMB_LOCAL": "SAN JUAN BAUTISTA", "TDIRE_LOCAL": "JR HUALLAGA SN", "CCENT_COMPU": "C45098", "DEPARTAMENTO": "SAN MARTIN", "PROVINCIA": "SAN MARTIN", "DISTRITO": "SHAPAJA", "CCOPIA_ACTA": "95D", "NNUME_HABILM": 236, "OBSERVACION": "CONTABILIZADAS NORMALES", "OBSERVACION_TXT": "ACTA ELECTORAL NORMAL", "N_CANDIDATOS": 0, "TOT_CIUDADANOS_VOTARON": 183}, "votos": [{"CCODI_AUTO": "00000014", "AUTORIDAD": "PARTIDO POLITICO NACIONAL PERU LIBRE", "NLISTA": "1", "congresal": "92", "CON_VALIDOS": "53.801", "CON_EMITIDOS": "50.273"}, {"CCODI_AUTO": "00000007", "AUTORIDAD": "FUERZA POPULAR", "NLISTA": "2", "congresal": "79", "CON_VALIDOS": "46.199", "CON_EMITIDOS": "43.169"}, {"CCODI_AUTO": null, "AUTORIDAD": "TOTAL VOTOS VALIDOS", "congresal": "171", "CON_VALIDOS": "100.000", "CON_EMITIDOS": "93.443"}, {"CCODI_AUTO": "80", "AUTORIDAD": "VOTOS EN BLANCO", "congresal": "2", "CON_EMITIDOS": "1.093", "CON_VALIDOS": null}, {"CCODI_AUTO": "80", "AUTORIDAD": "VOTOS NULOS", "congresal": "10", "CON_EMITIDOS": "5.464", "CON_VALIDOS": null}, {"CCODI_AUTO": "80", "AUTORIDAD": "VOTOS IMPUGNADOS", "congresal": "0", "CON_EMITIDOS": "0.000", "CON_VALIDOS": null}, {"CCODI_AUTO": null, "AUTORIDAD": "TOTAL VOTOS EMITIDOS", "congresal": "183", "CON_EMITIDOS": "100.000", "CON_VALIDOS": "93.443"}], "resoluciones": [], "imageActa": "https://presentacionsep2021-actas-resultados-prod.s3.amazonaws.com/AC/C45098/SEP/ACPREC4509807375695.PDF?X-Amz-Algorithm=AWS4-HMAC-SHA256&X-Amz-Credential=AKIAXQU6GNJSVXR2WUHM%2F20210611%2Fus-east-1%2Fs3%2Faws4_request&X-Amz-Date=20210611T234855Z&X-Amz-Expires=3600&X-Amz-SignedHeaders=host&X-Amz-Signature=95b0d84dc1e022543fa9a5115ae6935207a595dd204350f3c1f73ac1ff311181"}, "asistioNoVoto": "0", "realImages": "1"}}