{"procesos": {"generalPre": {"presidencial": {"CCODI_UBIGEO": "240105", "TNOMB_LOCAL": "ESTADIO CAMPOLO ALCALDE", "TDIRE_LOCAL": "AV HAYA DE LA TORRE SN", "CCENT_COMPU": "C45028", "DEPARTAMENTO": "CALLAO", "PROVINCIA": "CALLAO", "DISTRITO": "LA PERLA", "CCOPIA_ACTA": "96V", "NNUME_HABILM": 300, "OBSERVACION": "CONTABILIZADAS NORMALES", "OBSERVACION_TXT": "ACTA ELECTORAL NORMAL", "N_CANDIDATOS": 0, "TOT_CIUDADANOS_VOTARON": 233}, "votos": [{"CCODI_AUTO": "00000014", "AUTORIDAD": "PARTIDO POLITICO NACIONAL PERU LIBRE", "NLISTA": "1", "congresal": "50", "CON_VALIDOS": "22.936", "CON_EMITIDOS": "21.459"}, {"CCODI_AUTO": "00000007", "AUTORIDAD": "FUERZA POPULAR", "NLISTA": "2", "congresal": "168", "CON_VALIDOS": "77.064", "CON_EMITIDOS": "72.103"}, {"CCODI_AUTO": null, "AUTORIDAD": "TOTAL VOTOS VALIDOS", "congresal": "218", "CON_VALIDOS": "100.000", "CON_EMITIDOS": "93.562"}, {"CCODI_AUTO": "80", "AUTORIDAD": "VOTOS EN BLANCO", "congresal": "2", "CON_EMITIDOS": "0.858", "CON_VALIDOS": null}, {"CCODI_AUTO": "80", "AUTORIDAD": "VOTOS NULOS", "congresal": "13", "CON_EMITIDOS": "5.579", "CON_VALIDOS": null}, {"CCODI_AUTO": "80", "AUTORIDAD": "VOTOS IMPUGNADOS", "congresal": "0", "CON_EMITIDOS": "0.000", "CON_VALIDOS": null}, {"CCODI_AUTO": null, "AUTORIDAD": "TOTAL VOTOS EMITIDOS", "congresal": "233", "CON_EMITIDOS": "100.000", "CON_VALIDOS": "93.562"}], "resoluciones": [], "imageActa": "https://presentacionsep2021-actas-resultados-prod2.s3.amazonaws.com/AC/C45028/SEP/ACPREC4502807760996.PDF?X-Amz-Algorithm=AWS4-HMAC-SHA256&X-Amz-Credential=AKIAXQU6GNJSVXR2WUHM%2F20210612%2Fus-east-2%2Fs3%2Faws4_request&X-Amz-Date=20210612T000810Z&X-Amz-Expires=3600&X-Amz-SignedHeaders=host&X-Amz-Signature=4f7c2ea210e0c7f820a7d9816b4da65c85a358157b0ce963c6c2180b145f3d08"}, "asistioNoVoto": "0", "realImages": "1"}}