{"procesos": {"generalPre": {"presidencial": {"CCODI_UBIGEO": "071006", "TNOMB_LOCAL": "IE JEC OSCCOLLOPATA", "TDIRE_LOCAL": "CCPP HUASQUILLAY", "CCENT_COMPU": "C45031", "DEPARTAMENTO": "CUSCO", "PROVINCIA": "PARURO", "DISTRITO": "OMACHA", "CCOPIA_ACTA": "97B", "NNUME_HABILM": 252, "OBSERVACION": "CONTABILIZADAS NORMALES", "OBSERVACION_TXT": "ACTA ELECTORAL NORMAL", "N_CANDIDATOS": 0, "TOT_CIUDADANOS_VOTARON": 175}, "votos": [{"CCODI_AUTO": "00000014", "AUTORIDAD": "PARTIDO POLITICO NACIONAL PERU LIBRE", "NLISTA": "1", "congresal": "152", "CON_VALIDOS": "95.597", "CON_EMITIDOS": "86.857"}, {"CCODI_AUTO": "00000007", "AUTORIDAD": "FUERZA POPULAR", "NLISTA": "2", "congresal": "7", "CON_VALIDOS": "4.403", "CON_EMITIDOS": "4.000"}, {"CCODI_AUTO": null, "AUTORIDAD": "TOTAL VOTOS VALIDOS", "congresal": "159", "CON_VALIDOS": "100.000", "CON_EMITIDOS": "90.857"}, {"CCODI_AUTO": "80", "AUTORIDAD": "VOTOS EN BLANCO", "congresal": "3", "CON_EMITIDOS": "1.714", "CON_VALIDOS": null}, {"CCODI_AUTO": "80", "AUTORIDAD": "VOTOS NULOS", "congresal": "13", "CON_EMITIDOS": "7.429", "CON_VALIDOS": null}, {"CCODI_AUTO": "80", "AUTORIDAD": "VOTOS IMPUGNADOS", "congresal": "0", "CON_EMITIDOS": "0.000", "CON_VALIDOS": null}, {"CCODI_AUTO": null, "AUTORIDAD": "TOTAL VOTOS EMITIDOS", "congresal": "175", "CON_EMITIDOS": "100.000", "CON_VALIDOS": "90.857"}], "resoluciones": [], "imageActa": "https://presentacionsep2021-actas-resultados-prod2.s3.amazonaws.com/AC/C45031/SEP/ACPREC4503190123797.PDF?X-Amz-Algorithm=AWS4-HMAC-SHA256&X-Amz-Credential=AKIAXQU6GNJSVXR2WUHM%2F20210612%2Fus-east-2%2Fs3%2Faws4_request&X-Amz-Date=20210612T002514Z&X-Amz-Expires=3600&X-Amz-SignedHeaders=host&X-Amz-Signature=e491c2a9fd08b1a0e1af314a44d6bf304f92b961d3efc960a41883937b4d9439"}, "asistioNoVoto": "0", "realImages": "1"}}