{"procesos": {"generalPre": {"presidencial": {"CCODI_UBIGEO": "150603", "TNOMB_LOCAL": "IE 60082 MARIA ANTONIETA MENDOZA PINTO", "TDIRE_LOCAL": "CALLE CENTRO ALEGRIA SN", "CCENT_COMPU": "C45084", "DEPARTAMENTO": "LORETO", "PROVINCIA": "MARISCAL RAMON CASTILLA", "DISTRITO": "YAVARI", "CCOPIA_ACTA": "93B", "NNUME_HABILM": 158, "OBSERVACION": "CONTABILIZADAS NORMALES", "OBSERVACION_TXT": "ACTA ELECTORAL NORMAL", "N_CANDIDATOS": 0, "TOT_CIUDADANOS_VOTARON": 105}, "votos": [{"CCODI_AUTO": "00000014", "AUTORIDAD": "PARTIDO POLITICO NACIONAL PERU LIBRE", "NLISTA": "1", "congresal": "3", "CON_VALIDOS": "2.941", "CON_EMITIDOS": "2.857"}, {"CCODI_AUTO": "00000007", "AUTORIDAD": "FUERZA POPULAR", "NLISTA": "2", "congresal": "99", "CON_VALIDOS": "97.059", "CON_EMITIDOS": "94.286"}, {"CCODI_AUTO": null, "AUTORIDAD": "TOTAL VOTOS VALIDOS", "congresal": "102", "CON_VALIDOS": "100.000", "CON_EMITIDOS": "97.143"}, {"CCODI_AUTO": "80", "AUTORIDAD": "VOTOS EN BLANCO", "congresal": "3", "CON_EMITIDOS": "2.857", "CON_VALIDOS": null}, {"CCODI_AUTO": "80", "AUTORIDAD": "VOTOS NULOS", "congresal": "0", "CON_EMITIDOS": "0.000", "CON_VALIDOS": null}, {"CCODI_AUTO": "80", "AUTORIDAD": "VOTOS IMPUGNADOS", "congresal": "0", "CON_EMITIDOS": "0.000", "CON_VALIDOS": null}, {"CCODI_AUTO": null, "AUTORIDAD": "TOTAL VOTOS EMITIDOS", "congresal": "105", "CON_EMITIDOS": "100.000", "CON_VALIDOS": "97.143"}], "resoluciones": [], "imageActa": "https://presentacionsep2021-actas-resultados-prod2.s3.amazonaws.com/AC/C45084/SEP/ACPREC4508490248393.PDF?X-Amz-Algorithm=AWS4-HMAC-SHA256&X-Amz-Credential=AKIAXQU6GNJSVXR2WUHM%2F20210612%2Fus-east-2%2Fs3%2Faws4_request&X-Amz-Date=20210612T003345Z&X-Amz-Expires=3600&X-Amz-SignedHeaders=host&X-Amz-Signature=339d6d9c4be739c15958466b4ca0241767eb019091e8bcb18f50620dd81c82a5"}, "asistioNoVoto": "0", "realImages": "1"}}